LICENSE
MANIFEST.in
README.rst
setup.py
graphql/__init__.py
graphql/ast.py
graphql/exceptions.py
graphql/lexer.py
graphql/parser.py
graphql/parsetab.py
graphql_py.egg-info/PKG-INFO
graphql_py.egg-info/SOURCES.txt
graphql_py.egg-info/dependency_links.txt
graphql_py.egg-info/not-zip-safe
graphql_py.egg-info/pbr.json
graphql_py.egg-info/requires.txt
graphql_py.egg-info/top_level.txt