Metadata-Version: 1.1
Name: graphql-py
Version: 0.8.0
Summary: graphql-py: Parser for latest GraphQL specification
Home-page: https://github.com/ivelum/graphql-py/
Author: Denis Stebunov
Author-email: support@ivelum.com
License: The MIT License (MIT)
